stpy/__init__.py
stpy/config.py
stpy/summarize_gScholarAlerts.py
stpy/utils.py
stpy/crawl_web/save_image_from_web.py
stpy/crawl_web/trial.py
stpy-0.1.2.dist-info/METADATA
stpy-0.1.2.dist-info/WHEEL
stpy-0.1.2.dist-info/top_level.txt
stpy-0.1.2.dist-info/RECORD
