Metadata-Version: 2.4
Name: stpy
Version: 0.1.2
Summary: A Python package for data science and cheminformatics utilities.
Author-email: Lihua Deng <lihuad09@qq.com>
Requires-Python: >=3.12
Requires-Dist: pandas
Requires-Dist: numpy
Requires-Dist: matplotlib
Requires-Dist: seaborn
Requires-Dist: requests
Requires-Dist: rdkit
Requires-Dist: scikit-learn
Provides-Extra: dev
Requires-Dist: pytest; extra == "dev"
Requires-Dist: pytest-cov; extra == "dev"
Requires-Dist: coverage[toml]; extra == "dev"
